setup.py
./pyremotezip/__init__.py
./pyremotezip/remotezip.py
pyremotezip.egg-info/PKG-INFO
pyremotezip.egg-info/SOURCES.txt
pyremotezip.egg-info/dependency_links.txt
pyremotezip.egg-info/entry_points.txt
pyremotezip.egg-info/not-zip-safe
pyremotezip.egg-info/requires.txt
pyremotezip.egg-info/top_level.txt