Metadata-Version: 1.0
Name: pyremotezip
Version: 0.4
Summary: Extract files from remote ZIP archives
Home-page: https://github.com/fcvarela/pyremotezip/
Author: Filipe Varela
Author-email: fcvarela@gmail.com
License: BSD
Platform: UNKNOWN
